pyCompare/VERSION
pyCompare/__init__.py
pyCompare/_calculateConfidenceIntervals.py
pyCompare/_carkeetCIest.py
pyCompare/_detrend.py
pyCompare/_plotBlandAltman.py
pyCompare/_rangeFrameLocator.py
pyCompare-1.5.4.dist-info/LICENSE.txt
pyCompare-1.5.4.dist-info/METADATA
pyCompare-1.5.4.dist-info/WHEEL
pyCompare-1.5.4.dist-info/top_level.txt
pyCompare-1.5.4.dist-info/zip-safe
pyCompare-1.5.4.dist-info/RECORD
