Metadata-Version: 2.1
Name: pyCompare
Version: 1.5.4
Summary: Bland-Altman plots for Python
Home-page: https://github.com/jaketmp/pyCompare
Author: Jake TM Pearce
License: MIT
Platform: UNKNOWN
Classifier: Programming Language :: Python
Classifier: Programming Language :: Python :: 3.6
Classifier: Programming Language :: Python :: 3.7
Classifier: Programming Language :: Python :: 3.8
Classifier: Programming Language :: Python :: 3.9
Classifier: Intended Audience :: Science/Research
Classifier: License :: OSI Approved :: MIT License
Classifier: Operating System :: OS Independent
Classifier: Topic :: Scientific/Engineering :: Bio-Informatics
Classifier: Topic :: Scientific/Engineering :: Visualization
License-File: LICENSE.txt
Requires-Dist: numpy (>=1.18.1)
Requires-Dist: scipy (>=1.0.1)
Requires-Dist: matplotlib (>=3.0.2)
